xiaoya_downloader/__init__.py
xiaoya_downloader/attribute.py
xiaoya_downloader/command.py
xiaoya_downloader/download.py
xiaoya_downloader/resources.py
xiaoya_downloader/webserver.py
xiaoya_downloader/static/__init__.py
xiaoya_downloader/static/favicon.png
xiaoya_downloader/templates/__init__.py
xiaoya_downloader/templates/table.html
xiaoya_downloader/translate/__init__.py
xiaoya_downloader/translate/en.xlc
xiaoya_downloader/translate/zh-Hans.xlc
xiaoya_downloader/translate/zh-Hant.xlc
xiaoya_downloader-0.16.2.dist-info/LICENSE
xiaoya_downloader-0.16.2.dist-info/METADATA
xiaoya_downloader-0.16.2.dist-info/WHEEL
xiaoya_downloader-0.16.2.dist-info/entry_points.txt
xiaoya_downloader-0.16.2.dist-info/top_level.txt
xiaoya_downloader-0.16.2.dist-info/zip-safe
xiaoya_downloader-0.16.2.dist-info/RECORD
